citytrader
